{
  "NVDA": {
    "revenue": [
      {
        "label": "Q2 2018",
        "val": 3.21
      },
      {
        "label": "Q3 2018",
        "val": 3.12
      },
      {
        "label": "Q4 2018",
        "val": 3.18
      },
      {
        "label": "Q1 2019",
        "val": 2.21
      },
      {
        "label": "Q2 2019",
        "val": 2.22
      },
      {
        "label": "Q3 2019",
        "val": 2.58
      },
      {
        "label": "Q4 2019",
        "val": 3.01
      },
      {
        "label": "Q1 2020",
        "val": 3.1
      }
    ],
    "grossMargin": [],
    "opMargin": [],
    "fcf": [
      {
        "label": "Q2 2018",
        "val": 1.33
      },
      {
        "label": "Q2 2019",
        "val": 0.59
      },
      {
        "label": "Q2 2020",
        "val": 0.76
      },
      {
        "label": "Q2 2021",
        "val": 1.87
      },
      {
        "label": "Q2 2022",
        "val": 1.73
      },
      {
        "label": "Q2 2023",
        "val": 2.91
      },
      {
        "label": "Q2 2024",
        "val": 15.35
      },
      {
        "label": "Q2 2025",
        "val": 27.41
      }
    ],
    "debt": [],
    "cash": []
  },
  "META": {
    "revenue": [
      {
        "label": "Q3 2023",
        "val": 34.15
      },
      {
        "label": "Q1 2024",
        "val": 36.45
      },
      {
        "label": "Q2 2024",
        "val": 39.07
      },
      {
        "label": "Q3 2024",
        "val": 40.59
      },
      {
        "label": "Q1 2025",
        "val": 42.31
      },
      {
        "label": "Q2 2025",
        "val": 47.52
      },
      {
        "label": "Q3 2025",
        "val": 51.24
      },
      {
        "label": "Q1 2026",
        "val": 56.31
      }
    ],
    "grossMargin": [
      {
        "label": "Q3 2023",
        "val": 81.82
      },
      {
        "label": "Q1 2024",
        "val": 81.78
      },
      {
        "label": "Q2 2024",
        "val": 81.29
      },
      {
        "label": "Q3 2024",
        "val": 81.82
      },
      {
        "label": "Q1 2025",
        "val": 82.11
      },
      {
        "label": "Q2 2025",
        "val": 82.13
      },
      {
        "label": "Q3 2025",
        "val": 82.03
      },
      {
        "label": "Q1 2026",
        "val": 81.85
      }
    ],
    "opMargin": [
      {
        "label": "Q3 2023",
        "val": 40.26
      },
      {
        "label": "Q1 2024",
        "val": 37.91
      },
      {
        "label": "Q2 2024",
        "val": 38.01
      },
      {
        "label": "Q3 2024",
        "val": 42.74
      },
      {
        "label": "Q1 2025",
        "val": 41.48
      },
      {
        "label": "Q2 2025",
        "val": 43.01
      },
      {
        "label": "Q3 2025",
        "val": 40.09
      },
      {
        "label": "Q1 2026",
        "val": 40.61
      }
    ],
    "fcf": [
      {
        "label": "Q1 2019",
        "val": 5.47
      },
      {
        "label": "Q1 2020",
        "val": 7.44
      },
      {
        "label": "Q1 2021",
        "val": 7.94
      },
      {
        "label": "Q1 2022",
        "val": 8.64
      },
      {
        "label": "Q1 2023",
        "val": 7.18
      },
      {
        "label": "Q1 2024",
        "val": 12.85
      },
      {
        "label": "Q1 2025",
        "val": 11.09
      },
      {
        "label": "Q1 2026",
        "val": 13.23
      }
    ],
    "debt": [],
    "cash": []
  },
  "AMZN": {
    "revenue": [
      {
        "label": "Q3 2023",
        "val": 143.08
      },
      {
        "label": "Q1 2024",
        "val": 143.31
      },
      {
        "label": "Q2 2024",
        "val": 147.98
      },
      {
        "label": "Q3 2024",
        "val": 158.88
      },
      {
        "label": "Q1 2025",
        "val": 155.67
      },
      {
        "label": "Q2 2025",
        "val": 167.7
      },
      {
        "label": "Q3 2025",
        "val": 180.17
      },
      {
        "label": "Q1 2026",
        "val": 181.52
      }
    ],
    "grossMargin": [
      {
        "label": "Q3 2023",
        "val": 47.57
      },
      {
        "label": "Q1 2024",
        "val": 49.32
      },
      {
        "label": "Q2 2024",
        "val": 50.14
      },
      {
        "label": "Q3 2024",
        "val": 49.03
      },
      {
        "label": "Q1 2025",
        "val": 50.55
      },
      {
        "label": "Q2 2025",
        "val": 51.81
      },
      {
        "label": "Q3 2025",
        "val": 50.79
      },
      {
        "label": "Q1 2026",
        "val": 51.82
      }
    ],
    "opMargin": [
      {
        "label": "Q3 2023",
        "val": 7.82
      },
      {
        "label": "Q1 2024",
        "val": 10.68
      },
      {
        "label": "Q2 2024",
        "val": 9.91
      },
      {
        "label": "Q3 2024",
        "val": 10.96
      },
      {
        "label": "Q1 2025",
        "val": 11.83
      },
      {
        "label": "Q2 2025",
        "val": 11.43
      },
      {
        "label": "Q3 2025",
        "val": 9.67
      },
      {
        "label": "Q1 2026",
        "val": 13.14
      }
    ],
    "fcf": [
      {
        "label": "Q3 2023",
        "val": 21.22
      },
      {
        "label": "Q1 2024",
        "val": 18.99
      },
      {
        "label": "Q2 2024",
        "val": 25.28
      },
      {
        "label": "Q3 2024",
        "val": 25.97
      },
      {
        "label": "Q1 2025",
        "val": 17.02
      },
      {
        "label": "Q2 2025",
        "val": 32.52
      },
      {
        "label": "Q3 2025",
        "val": 35.52
      },
      {
        "label": "Q1 2026",
        "val": 26.03
      }
    ],
    "debt": [],
    "cash": []
  },
  "YPF": {
    "revenue": [],
    "grossMargin": [],
    "opMargin": [],
    "fcf": [],
    "debt": [],
    "cash": []
  }
}